my_own_package/__init__.py
bogdan_project_hello-0.1.0.dist-info/METADATA
bogdan_project_hello-0.1.0.dist-info/WHEEL
bogdan_project_hello-0.1.0.dist-info/top_level.txt
bogdan_project_hello-0.1.0.dist-info/RECORD
