Metadata-Version: 2.1
Name: bogdan-project-hello
Version: 0.1.0
Summary: salutare
Author: bogdan
Author-email: bogdanmurgea@gmail.com
License: UNKNOWN
Platform: UNKNOWN
